cellcollective.py
espresso_setup.py
itstools.py
itstools_setup.py
nusmv.py
nusmv_setup.py
colomoto/__init__.py
colomoto/helpers.py
colomoto/minibn.py
colomoto/modelchecking.py
colomoto/setup_helper.py
colomoto/temporal_logics.py
colomoto/types.py
colomoto_jupyter/__init__.py
colomoto_jupyter/config.py
colomoto_jupyter/formatters.py
colomoto_jupyter/io.py
colomoto_jupyter/ipylab.py
colomoto_jupyter/sessionfiles.py
colomoto_jupyter/ui.py
colomoto_jupyter/upload.py
colomoto_jupyter/widget_utils.py
colomoto_jupyter-0.9.1.dist-info/METADATA
colomoto_jupyter-0.9.1.dist-info/WHEEL
colomoto_jupyter-0.9.1.dist-info/top_level.txt
colomoto_jupyter-0.9.1.dist-info/RECORD
