Metadata-Version: 2.4
Name: colomoto_jupyter
Version: 0.9.1
Summary: CoLoMoTo helper functions for Juypter integration
Home-page: https://github.com/colomoto/colomoto-jupyter
Author: Loïc Paulevé
Author-email: loic.pauleve@ens-cachan.org
License: LGPL v3+/CeCILL-C
Keywords: jupyter,computational systems biology
Classifier: Intended Audience :: Science/Research
Classifier: Topic :: Scientific/Engineering :: Bio-Informatics
Requires-Dist: beautifulsoup4
Requires-Dist: boolean.py
Requires-Dist: networkx>=2.0
Requires-Dist: pandas
Requires-Dist: pydot
Dynamic: author
Dynamic: author-email
Dynamic: classifier
Dynamic: description
Dynamic: home-page
Dynamic: keywords
Dynamic: license
Dynamic: requires-dist
Dynamic: summary
